LICENSE
MANIFEST.in
README.rst
requirements.txt
setup.cfg
setup.py
pyod/__init__.py
pyod/version.py
pyod.egg-info/PKG-INFO
pyod.egg-info/SOURCES.txt
pyod.egg-info/dependency_links.txt
pyod.egg-info/requires.txt
pyod.egg-info/top_level.txt
pyod/models/__init__.py
pyod/models/abod.py
pyod/models/alad.py
pyod/models/anogan.py
pyod/models/auto_encoder.py
pyod/models/base.py
pyod/models/base_dl.py
pyod/models/cblof.py
pyod/models/cd.py
pyod/models/cof.py
pyod/models/combination.py
pyod/models/copod.py
pyod/models/deep_svdd.py
pyod/models/dif.py
pyod/models/ecod.py
pyod/models/feature_bagging.py
pyod/models/gaal_base.py
pyod/models/gmm.py
pyod/models/hbos.py
pyod/models/iforest.py
pyod/models/inne.py
pyod/models/kde.py
pyod/models/knn.py
pyod/models/kpca.py
pyod/models/lmdd.py
pyod/models/loci.py
pyod/models/loda.py
pyod/models/lof.py
pyod/models/lscp.py
pyod/models/lunar.py
pyod/models/mad.py
pyod/models/mcd.py
pyod/models/mo_gaal.py
pyod/models/ocsvm.py
pyod/models/pca.py
pyod/models/qmcd.py
pyod/models/rgraph.py
pyod/models/rod.py
pyod/models/sampling.py
pyod/models/sklearn_base.py
pyod/models/so_gaal.py
pyod/models/so_gaal_new.py
pyod/models/sod.py
pyod/models/sos.py
pyod/models/suod.py
pyod/models/thresholds.py
pyod/models/vae.py
pyod/models/xgbod.py
pyod/utils/__init__.py
pyod/utils/data.py
pyod/utils/example.py
pyod/utils/stat_models.py
pyod/utils/torch_utility.py
pyod/utils/utility.py