Metadata-Version: 2.1
Name: pyod
Version: 2.0.1
Summary: A Comprehensive and Scalable Python Library for Outlier Detection (Anomaly Detection)
Home-page: https://github.com/yzhao062/pyod
Download-URL: https://github.com/yzhao062/pyod/archive/master.zip
Author: Yue Zhao
Author-email: yzhao062@gmail.com
Keywords: outlier detection,anomaly detection,outlier ensembles,data mining,neural networks
Classifier: Development Status :: 6 - Mature
Classifier: Intended Audience :: Education
Classifier: Intended Audience :: Financial and Insurance Industry
Classifier: Intended Audience :: Science/Research
Classifier: Intended Audience :: Developers
Classifier: Intended Audience :: Information Technology
Classifier: License :: OSI Approved :: BSD License
Classifier: Programming Language :: Python :: 3.6
Classifier: Programming Language :: Python :: 3.7
Classifier: Programming Language :: Python :: 3.8
Classifier: Programming Language :: Python :: 3.9
Classifier: Programming Language :: Python :: 3.10
Classifier: Programming Language :: Python :: 3.11
Classifier: Programming Language :: Python :: 3.12
License-File: LICENSE
Requires-Dist: joblib
Requires-Dist: matplotlib
Requires-Dist: numpy>=1.19
Requires-Dist: numba>=0.51
Requires-Dist: scipy>=1.5.1
Requires-Dist: scikit-learn>=0.22.0
